odoo8_addon_base_location_geonames_import-8.0.1.0.1-py2.7-nspkg.pth
odoo8_addon_base_location_geonames_import-8.0.1.0.1.dist-info/top_level.txt
odoo8_addon_base_location_geonames_import-8.0.1.0.1.dist-info/WHEEL
odoo8_addon_base_location_geonames_import-8.0.1.0.1.dist-info/RECORD
odoo8_addon_base_location_geonames_import-8.0.1.0.1.dist-info/metadata.json
odoo8_addon_base_location_geonames_import-8.0.1.0.1.dist-info/DESCRIPTION.rst
odoo8_addon_base_location_geonames_import-8.0.1.0.1.dist-info/METADATA
odoo8_addon_base_location_geonames_import-8.0.1.0.1.dist-info/namespace_packages.txt
odoo_addons/base_location_geonames_import/__openerp__.py
odoo_addons/base_location_geonames_import/__init__.py
odoo_addons/base_location_geonames_import/README.rst
odoo_addons/base_location_geonames_import/i18n/it.po
odoo_addons/base_location_geonames_import/i18n/es.po
odoo_addons/base_location_geonames_import/i18n/sl.po
odoo_addons/base_location_geonames_import/i18n/base_location_geonames_import.pot
odoo_addons/base_location_geonames_import/i18n/nl.po
odoo_addons/base_location_geonames_import/i18n/de.po
odoo_addons/base_location_geonames_import/i18n/fr.po
odoo_addons/base_location_geonames_import/i18n/pt_BR.po
odoo_addons/base_location_geonames_import/i18n/fi.po
odoo_addons/base_location_geonames_import/wizard/geonames_import.py
odoo_addons/base_location_geonames_import/wizard/__init__.py
odoo_addons/base_location_geonames_import/wizard/geonames_import_view.xml
odoo_addons/base_location_geonames_import/tests/test_base_location_geonames_import.py
odoo_addons/base_location_geonames_import/tests/__init__.py
odoo_addons/base_location_geonames_import/static/description/icon.svg
odoo_addons/base_location_geonames_import/static/description/icon.png
